README.md
setup.py
memect_http_error/__init__.py
memect_http_error.egg-info/PKG-INFO
memect_http_error.egg-info/SOURCES.txt
memect_http_error.egg-info/dependency_links.txt
memect_http_error.egg-info/top_level.txt
memect_http_error.egg-info/zip-safe