Metadata-Version: 1.1
Name: memect-http-error
Version: 0.0.7
Summary: error code package for memect.co
Home-page: https://pypi.python.org/pypi/memect-http-error
Author: @nanhuijuan
Author-email: nanhuijuan@memect.co
License: MIT
Keywords: http error code
Platform: UNKNOWN
Classifier: License :: OSI Approved :: MIT License
Classifier: Programming Language :: Python
Classifier: Intended Audience :: Developers
Classifier: Operating System :: OS Independent
